<?xml version="1.0" encoding="utf-8"?>
<LanguageData>
<!-- Demon privates parts -->
<DemonTentaclePenis.label>демонічні шупальця</DemonTentaclePenis.label>
<DemonTentaclePenis.description>Довгі та гнучкі, постійно виділяють дивну рідину. Не підходить для людей.</DemonTentaclePenis.description>
<DemonPenis.label>демонічний пеніс</DemonPenis.label>
<DemonPenis.description>Зазвичайного людського розміру, постійно виділяє дивну рідину. Не підходить для людей.</DemonPenis.description>
<Demonвагина.label>демонічна вагіна</Demonвагина.label>
<Demonвагина.description>Наповнена безліччю щупалець, які постійно виділяють дивну рідину. Не підходить для людей.</Demonвагина.description>
<DemonAnus.label>демонічний анус</DemonAnus.label>
<DemonAnus.description>Наповнений безліччю щупалець. Не підходить для людей.</DemonAnus.description>
</LanguageData>